CHANGES.rst
LICENSE.txt
MANIFEST.in
README.rst
setup.py
src/bst/__init__.py
src/bst.pygasus.i18n.egg-info/PKG-INFO
src/bst.pygasus.i18n.egg-info/SOURCES.txt
src/bst.pygasus.i18n.egg-info/dependency_links.txt
src/bst.pygasus.i18n.egg-info/entry_points.txt
src/bst.pygasus.i18n.egg-info/namespace_packages.txt
src/bst.pygasus.i18n.egg-info/not-zip-safe
src/bst.pygasus.i18n.egg-info/requires.txt
src/bst.pygasus.i18n.egg-info/top_level.txt
src/bst/pygasus/__init__.py
src/bst/pygasus/i18n/__init__.py
src/bst/pygasus/i18n/configure.zcml
src/bst/pygasus/i18n/extractor.py
src/bst/pygasus/i18n/translationservice.py
src/bst/pygasus/i18n/resources/bst.pygasus.i18n.js