Metadata-Version: 1.1
Name: bst.pygasus.i18n
Version: 1.0.1
Summary: provide translations for bst.pygasus framework
Home-page: https://github.com/bielbienne/bst.pygasus.i18n
Author: codeix
Author-email: samuel.riolo@biel-bienne.ch
License: ZPL 2.1
Keywords: pygasus web framework extjs
Platform: UNKNOWN
Classifier: Programming Language :: Python :: 3
Classifier: Natural Language :: English
Classifier: License :: OSI Approved :: Zope Public License
Classifier: Operating System :: OS Independent
Classifier: Development Status :: 4 - Beta
